{"stats":{"total":288,"passed":285,"skipped":3,"new":2},"status":"passed","newTests":[{"id":"c4577f558bafaaf6c957ed62ea1211ea","name":"Extract search query `baseUrl` from task","status":"passed","duration":1},{"id":"7695d8073e523a569c79b562d510f150","name":"Extract search query `baseUrl` from task","status":"passed","duration":0}],"flakyTests":[],"retryTests":[],"checks":[],"name":"greedy-token Tests","duration":11823,"createdAt":1783614415192,"plugin":"Awesome","meta":{"reportId":"08764fa7-0e3b-4215-a2bf-5b0838f64c2a","singleFile":false,"withTestResultsLinks":true},"pluginId":"awesome","pullRequestHref":"","jobHref":"https://github.com/svasenkov/greedy-token/actions/runs/29033382667","href":"awesome/"}